ap_altair_theme/__init__.py
ap_altair_theme/main.py
ap_altair_theme-0.0.3.dist-info/LICENSE
ap_altair_theme-0.0.3.dist-info/METADATA
ap_altair_theme-0.0.3.dist-info/WHEEL
ap_altair_theme-0.0.3.dist-info/top_level.txt
ap_altair_theme-0.0.3.dist-info/RECORD
