Metadata-Version: 2.1
Name: ap-altair-theme
Version: 0.0.3
Summary: A package that formats Altair charts to AP visual style.
Home-page: https://datateam.inside.ap.org/
Author: Kavish Harjai
Author-email: kharjai@ap.org
Classifier: Development Status :: 4 - Beta
Classifier: License :: OSI Approved :: MIT License
Classifier: Operating System :: OS Independent
Classifier: Programming Language :: Python :: 3
Classifier: Topic :: Multimedia :: Graphics :: Presentation
Requires-Python: >=3.7
License-File: LICENSE
